simplify_docx/__init__.py
simplify_docx/elements/__init__.py
simplify_docx/elements/base.py
simplify_docx/elements/body.py
simplify_docx/elements/document.py
simplify_docx/elements/form.py
simplify_docx/elements/paragraph.py
simplify_docx/elements/run_contents.py
simplify_docx/elements/table.py
simplify_docx/iterators/__init__.py
simplify_docx/iterators/body.py
simplify_docx/iterators/document.py
simplify_docx/iterators/generic.py
simplify_docx/iterators/paragraph.py
simplify_docx/iterators/run.py
simplify_docx/iterators/table.py
simplify_docx/types/__init__.py
simplify_docx/types/fragment.py
simplify_docx/utils/__init__.py
simplify_docx/utils/friendly_names.py
simplify_docx/utils/paragrapy_style.py
simplify_docx/utils/set_options.py
simplify_docx/utils/tag.py
simplify_docx/utils/walk.py
simplify_docx/utils/warnings.py
simplify_docx-0.1.2.dist-info/LICENSE
simplify_docx-0.1.2.dist-info/METADATA
simplify_docx-0.1.2.dist-info/WHEEL
simplify_docx-0.1.2.dist-info/entry_points.txt
simplify_docx-0.1.2.dist-info/top_level.txt
simplify_docx-0.1.2.dist-info/RECORD
